T0/__init__.py
T0/ConditionUpload/ConditionUploadAPI.py
T0/ConditionUpload/__init__.py
T0/ConditionUpload/upload.py
T0/JobSplitting/AlcaHarvest.py
T0/JobSplitting/Condition.py
T0/JobSplitting/Express.py
T0/JobSplitting/ExpressMerge.py
T0/JobSplitting/Repack.py
T0/JobSplitting/RepackMerge.py
T0/JobSplitting/__init__.py
T0/RunConfig/RunConfigAPI.py
T0/RunConfig/Tier0Config.py
T0/RunConfig/__init__.py
T0/RunLumiCloseout/RunLumiCloseoutAPI.py
T0/RunLumiCloseout/__init__.py
T0/StorageManager/StorageManagerAPI.py
T0/StorageManager/__init__.py
T0/WMBS/__init__.py
T0/WMBS/Oracle/Create.py
T0/WMBS/Oracle/__init__.py
T0/WMBS/Oracle/ConditionUpload/CompleteFiles.py
T0/WMBS/Oracle/ConditionUpload/FinishPCLforEmptyExpress.py
T0/WMBS/Oracle/ConditionUpload/GetConditions.py
T0/WMBS/Oracle/ConditionUpload/GetRunStopTime.py
T0/WMBS/Oracle/ConditionUpload/IsPromptCalibrationFinished.py
T0/WMBS/Oracle/ConditionUpload/MarkPromptCalibrationFinished.py
T0/WMBS/Oracle/ConditionUpload/__init__.py
T0/WMBS/Oracle/JobSplitting/InsertPromptCalibrationFile.py
T0/WMBS/Oracle/JobSplitting/InsertSplitLumis.py
T0/WMBS/Oracle/JobSplitting/__init__.py
T0/WMBS/Oracle/RunConfig/FindRecoRelease.py
T0/WMBS/Oracle/RunConfig/FindRecoReleaseDatasets.py
T0/WMBS/Oracle/RunConfig/GetExpressConfig.py
T0/WMBS/Oracle/RunConfig/GetHLTConfig.py
T0/WMBS/Oracle/RunConfig/GetPhEDExConfig.py
T0/WMBS/Oracle/RunConfig/GetRecoConfig.py
T0/WMBS/Oracle/RunConfig/GetRepackConfig.py
T0/WMBS/Oracle/RunConfig/GetRunInfo.py
T0/WMBS/Oracle/RunConfig/GetStreamDatasetTriggers.py
T0/WMBS/Oracle/RunConfig/GetStreamDatasets.py
T0/WMBS/Oracle/RunConfig/GetStreamOnlineVersion.py
T0/WMBS/Oracle/RunConfig/GetStreamStyle.py
T0/WMBS/Oracle/RunConfig/InsertCMSSWVersion.py
T0/WMBS/Oracle/RunConfig/InsertDatasetScenario.py
T0/WMBS/Oracle/RunConfig/InsertDatasetTrigger.py
T0/WMBS/Oracle/RunConfig/InsertExpressConfig.py
T0/WMBS/Oracle/RunConfig/InsertLumiSection.py
T0/WMBS/Oracle/RunConfig/InsertPhEDExConfig.py
T0-4.0.0.dist-info/LICENSE
T0-4.0.0.dist-info/METADATA
T0-4.0.0.dist-info/NOTICE
T0-4.0.0.dist-info/WHEEL
T0-4.0.0.dist-info/top_level.txt
T0-4.0.0.dist-info/RECORD
